flake8_plone_api.py
flake8_plone_api-1.6.0.dist-info/METADATA
flake8_plone_api-1.6.0.dist-info/WHEEL
flake8_plone_api-1.6.0.dist-info/entry_points.txt
flake8_plone_api-1.6.0.dist-info/licenses/LICENSE
flake8_plone_api-1.6.0.dist-info/RECORD
